fieldspy/__init__.py
fieldspy/petrophysics/__init__.py
fieldspy/petrophysics/geomechanics/__init__.py
fieldspy/petrophysics/geomechanics/stress_state.py
fieldspy/petrophysics/tracks/__init__.py
fieldspy/petrophysics/tracks/caltrack.py
fieldspy/petrophysics/tracks/cbltrack.py
fieldspy/petrophysics/tracks/dntrack.py
fieldspy/petrophysics/tracks/flagtrack.py
fieldspy/petrophysics/tracks/fmtrack.py
fieldspy/petrophysics/tracks/gastrack.py
fieldspy/petrophysics/tracks/grtrack.py
fieldspy/petrophysics/tracks/khtrack.py
fieldspy/petrophysics/tracks/ktrack.py
fieldspy/petrophysics/tracks/lithotrack.py
fieldspy/petrophysics/tracks/oilshowtrack.py
fieldspy/petrophysics/tracks/phietrack.py
fieldspy/petrophysics/tracks/restrack.py
fieldspy/petrophysics/tracks/swtrack.py
fieldspy/petrophysics/tracks/track.py
fieldspy/petrophysics/tracks/utils.py
fieldspy/petrophysics/tracks/vshtrack.py
fieldspy/petrophysics/workflows/__init__.py
fieldspy/petrophysics/workflows/estimator.py
fieldspy/petrophysics/workflows/petroequations.py
fieldspy/petrophysics/workflows/plotrecipes.py
fieldspy/wells/__init__.py
fieldspy/wells/checkarrays.py
fieldspy/wells/correlation.py
fieldspy/wells/data_onboarding_map.py
fieldspy/wells/depthmodel.py
fieldspy/wells/formations.py
fieldspy/wells/geo_utils.py
fieldspy/wells/interpolate.py
fieldspy/wells/log.py
fieldspy/wells/mincurve.py
fieldspy/wells/perforations.py
fieldspy/wells/pressures.py
fieldspy/wells/production.py
fieldspy/wells/projection.py
fieldspy/wells/survey.py
fieldspy/wells/tools.py
fieldspy/wells/units.py
fieldspy/wells/wells.py
fieldspy/wfm/__init__.py
fieldspy/wfm/models.py
fieldspy-0.1.12.dist-info/LICENSE
fieldspy-0.1.12.dist-info/WHEEL
fieldspy-0.1.12.dist-info/METADATA
fieldspy-0.1.12.dist-info/RECORD
