Metadata-Version: 2.1
Name: fieldspy
Version: 0.1.12
Summary: Well Logs Tool for Oil & Gas
License: MIT
Author: Santiago Cuervo
Requires-Python: >=3.7.1,<3.10
Classifier: License :: OSI Approved :: MIT License
Classifier: Programming Language :: Python :: 3
Classifier: Programming Language :: Python :: 3.8
Classifier: Programming Language :: Python :: 3.9
Requires-Dist: PyYAML (>=5.4.1,<6.0.0)
Requires-Dist: Rtree (>=1.0.0,<2.0.0)
Requires-Dist: SQLAlchemy (>=1.4.23,<2.0.0)
Requires-Dist: Shapely (>=1.7.1,<2.0.0)
Requires-Dist: folium (>=0.12.1,<0.13.0)
Requires-Dist: geopandas (>=0.10.2,<0.11.0)
Requires-Dist: lasio (>=0.29,<0.30)
Requires-Dist: mapclassify (>=2.4.3,<3.0.0)
Requires-Dist: matplotlib (>=3.3.4,<4.0.0)
Requires-Dist: numpy (>=1.20.1,<2.0.0)
Requires-Dist: openpyxl (>=3.0.9,<4.0.0)
Requires-Dist: pandas (>=1.2.3,<2.0.0)
Requires-Dist: plotly (>=5.4.0,<6.0.0)
Requires-Dist: pydantic (>=1.8.1,<2.0.0)
Requires-Dist: pyproj (>=3.1.0,<4.0.0)
Requires-Dist: pyvista (>=0.32.1,<0.33.0)
Requires-Dist: scipy (>=1.6.1,<2.0.0)
Requires-Dist: seaborn (>=0.11.1,<0.12.0)
Requires-Dist: wellschematicspy (>=0.1.1,<0.2.0)
